pysasf/__init__.py
pysasf/basindata.py
pysasf/clarkeminella.py
pysasf/distances.py
pysasf/plots.py
pysasf/readers.py
pysasf/solvers.py
pysasf/stats.py
pysasf/utils.py
PySASF-0.0.5.dist-info/LICENSE
PySASF-0.0.5.dist-info/METADATA
PySASF-0.0.5.dist-info/WHEEL
PySASF-0.0.5.dist-info/top_level.txt
PySASF-0.0.5.dist-info/RECORD
