Metadata-Version: 2.1
Name: PySASF
Version: 0.0.5
Summary: A Python package for Source Apportionment with Sediment Fingerprinting.
Author-email: Tiago M Buriol <tiagoburiol@gmail.com>
Maintainer-email: Tiago M Buriol <tiagoburiol@gmail.com>
Project-URL: Homepage, https://github.com/tiagoburiol/PySASF
Project-URL: Issues, https://github.com/pypa/pysasf/issues
Classifier: Programming Language :: Python :: 3
Classifier: License :: OSI Approved :: MIT No Attribution License (MIT-0)
Classifier: Operating System :: OS Independent
Requires-Python: >=3.8
License-File: LICENSE
